llm_nosrun.py
llm_nosrun-0.2.dist-info/LICENSE
llm_nosrun-0.2.dist-info/METADATA
llm_nosrun-0.2.dist-info/WHEEL
llm_nosrun-0.2.dist-info/entry_points.txt
llm_nosrun-0.2.dist-info/top_level.txt
llm_nosrun-0.2.dist-info/RECORD
