Metadata-Version: 2.1
Name: llm-nosrun
Version: 0.2
Summary: LLM plugin for models hosted by NOS Cloud
Author: Sudeep Pillai
License: Apache-2.0
Project-URL: Homepage, https://github.com/autonomi-ai/llm-nosrun
Project-URL: Changelog, https://github.com/autonomi-ai/llm-nosrun/releases
Project-URL: Issues, https://github.com/autonomi-ai/llm-nosrun/issues
Project-URL: CI, https://github.com/autonomi-ai/llm-nosrun/actions
Classifier: License :: OSI Approved :: Apache Software License
License-File: LICENSE
Requires-Dist: llm >=0.8
Provides-Extra: test
Requires-Dist: pytest ; extra == 'test'
Requires-Dist: pytest-httpx ; extra == 'test'
